numalogic/__init__.py
numalogic/_constants.py
numalogic/backtest/__init__.py
numalogic/backtest/_constants.py
numalogic/backtest/_prom.py
numalogic/base.py
numalogic/blocks/__init__.py
numalogic/blocks/_base.py
numalogic/blocks/_nn.py
numalogic/blocks/_transform.py
numalogic/blocks/pipeline.py
numalogic/config/__init__.py
numalogic/config/_config.py
numalogic/config/factory.py
numalogic/connectors/__init__.py
numalogic/connectors/_base.py
numalogic/connectors/_config.py
numalogic/connectors/druid/__init__.py
numalogic/connectors/druid/_druid.py
numalogic/connectors/druid/aggregators.py
numalogic/connectors/druid/postaggregator.py
numalogic/connectors/exceptions.py
numalogic/connectors/prometheus.py
numalogic/connectors/rds/__init__.py
numalogic/connectors/rds/_base.py
numalogic/connectors/rds/_rds.py
numalogic/connectors/rds/db/__init__.py
numalogic/connectors/rds/db/factory.py
numalogic/connectors/rds/db/mysql_fetcher.py
numalogic/connectors/redis.py
numalogic/connectors/utils/__init__.py
numalogic/connectors/utils/aws/__init__.py
numalogic/connectors/utils/aws/boto3_client_manager.py
numalogic/connectors/utils/aws/config.py
numalogic/connectors/utils/aws/db_configurations.py
numalogic/connectors/utils/aws/exceptions.py
numalogic/connectors/utils/aws/sts_client_manager.py
numalogic/connectors/utils/enum.py
numalogic/connectors/wavefront.py
numalogic/models/__init__.py
numalogic/models/autoencoder/__init__.py
numalogic/models/autoencoder/base.py
numalogic/models/autoencoder/variants/__init__.py
numalogic/models/autoencoder/variants/conv.py
numalogic/models/autoencoder/variants/icvanilla.py
numalogic/models/autoencoder/variants/lstm.py
numalogic/models/autoencoder/variants/transformer.py
numalogic/models/autoencoder/variants/vanilla.py
numalogic/models/forecast/__init__.py
numalogic/models/forecast/variants/__init__.py
numalogic/models/forecast/variants/naive.py
numalogic/models/threshold/__init__.py
numalogic/models/threshold/_mahalanobis.py
numalogic-0.13.2.dist-info/LICENSE
numalogic-0.13.2.dist-info/METADATA
numalogic-0.13.2.dist-info/WHEEL
numalogic-0.13.2.dist-info/RECORD
