Metadata-Version: 2.1
Name: numalogic
Version: 0.13.2
Summary: Collection of operational Machine Learning models and tools.
Home-page: https://numalogic.numaproj.io/
License: Apache-2.0
Author: Numalogic Developers
Maintainer: Avik Basu
Maintainer-email: avikbasu93@gmail.com
Requires-Python: >=3.9,<3.13
Classifier: Intended Audience :: Developers
Classifier: License :: OSI Approved :: Apache Software License
Classifier: Programming Language :: Python :: 3
Classifier: Programming Language :: Python :: 3.9
Classifier: Programming Language :: Python :: 3.10
Classifier: Programming Language :: Python :: 3.11
Classifier: Programming Language :: Python :: 3.12
Classifier: Topic :: Scientific/Engineering :: Artificial Intelligence
Classifier: Topic :: Software Development :: Libraries
Provides-Extra: druid
Provides-Extra: dynamodb
Provides-Extra: mlflow
Provides-Extra: rds
Provides-Extra: redis
Requires-Dist: PyMySQL (>=1.1.0,<2.0.0) ; extra == "rds"
Requires-Dist: boto3 (>=1.24.64,<2.0.0) ; extra == "dynamodb" or extra == "rds"
Requires-Dist: cachetools (>=5.3.0,<6.0.0)
Requires-Dist: mlflow-skinny (>=2.0,<3.0) ; extra == "mlflow"
Requires-Dist: numalogic-prometheus (>=0.8,<0.9)
Requires-Dist: numpy (>=1.26,<2.0)
Requires-Dist: omegaconf (>=2.3.0,<3.0.0)
Requires-Dist: orjson (>=3.9,<4.0)
Requires-Dist: pandas[performance] (>=2.0,<3.0)
Requires-Dist: prometheus_client (>=0.18.0,<0.19.0)
Requires-Dist: pydruid (>=0.6,<0.7) ; extra == "druid"
Requires-Dist: pynumaflow (>=0.8,<0.9)
Requires-Dist: redis[hiredis] (>=5.0,<6.0) ; extra == "redis"
Requires-Dist: scikit-learn (>=1.3,<2.0)
Requires-Dist: structlog (>=24.1.0,<25.0.0)
Requires-Dist: wavefront-api-client (>=2.202.2,<3.0.0)
Project-URL: Documentation, https://numalogic.numaproj.io/
Project-URL: Repository, https://github.com/numaproj/numalogic
